MANIFEST.in
README.rst
setup.py
api/__init__.py
api/admin.py
api/apps.py
api/models.py
api/permissions.py
api/serializers.py
api/tests.py
api/urls.py
api/views.py
django_restapi_test.egg-info/PKG-INFO
django_restapi_test.egg-info/SOURCES.txt
django_restapi_test.egg-info/dependency_links.txt
django_restapi_test.egg-info/top_level.txt
docs/blank.txt